{"data_mtime": 1669984277, "dep_lines": [1, 1, 1, 1], "dep_prios": [5, 30, 30, 30], "dependencies": ["builtins", "_typeshed", "abc", "typing"], "hash": "de52983cf438b367cc0c0b68e397284caffb60a8d1246462684e2ab8f353a783", "id": "NotVerySecure", "ignore_all": false, "interface_hash": "121b5569b32100ba903c6e4a492fb4a37411655dd2d362b1f5591f361bd47e6b", "mtime": 1669984290, "options": {"allow_redefinition": false, "allow_untyped_globals": false, "always_false": [], "always_true": [], "bazel": false, "check_untyped_defs": false, "disable_error_code": [], "disabled_error_codes": [], "disallow_any_decorated": false, "disallow_any_explicit": false, "disallow_any_expr": false, "disallow_any_generics": false, "disallow_any_unimported": false, "disallow_incomplete_defs": false, "disallow_subclassing_any": false, "disallow_untyped_calls": false, "disallow_untyped_decorators": false, "disallow_untyped_defs": false, "enable_error_code": [], "enabled_error_codes": [], "follow_imports": "silent", "follow_imports_for_stubs": false, "ignore_errors": false, "ignore_missing_imports": true, "implicit_reexport": true, "local_partial_types": false, "mypyc": false, "no_implicit_optional": false, "platform": "win32", "plugins": [], "show_none_errors": true, "strict_concatenate": false, "strict_equality": false, "strict_optional": true, "strict_optional_whitelist": null, "warn_no_return": true, "warn_return_any": false, "warn_unreachable": false, "warn_unused_ignores": false}, "path": "c:\\Users\\matheus.maschietto\\Documents\\GitHub\\codeWarsChalanges\\pythonChallenges\\NotVerySecure.py", "plugin_data": null, "size": 515, "suppressed": [], "version_id": "0.982"}